pvat/__init__.py
pvat/estimators.py
pvat/py.typed
pvat/utilities.py
pvat/tests/__init__.py
pvat/tests/test_estimators.py
pvat/tests/test_utilities.py
pvat-0.0.0.dev2.dist-info/LICENSE
pvat-0.0.0.dev2.dist-info/METADATA
pvat-0.0.0.dev2.dist-info/WHEEL
pvat-0.0.0.dev2.dist-info/top_level.txt
pvat-0.0.0.dev2.dist-info/RECORD
